{
  "a": ["q", "w", "s", "z"],
  "b": ["v", "g", "h", "n"],
  "c": ["x", "d", "f", "v"],
  "d": ["s", "e", "r", "f", "c", "x"],
  "e": ["w", "r", "d", "s"],
  "f": ["d", "r", "t", "g", "v", "c"],
  "g": ["f", "t", "y", "h", "b", "v"],
  "h": ["g", "y", "u", "j", "n", "b"],
  "i": ["u", "o", "k", "j"],
  "j": ["h", "u", "i", "k", "n", "m"],
  "k": ["j", "i", "o", "l", "m"],
  "l": ["k", "o", "p"],
  "m": ["n", "j", "k"],
  "n": ["b", "h", "j", "m"],
  "o": ["i", "p", "l", "k"],
  "p": ["o", "l"],
  "q": ["w", "a"],
  "r": ["e", "t", "f", "d"],
  "s": ["a", "w", "e", "d", "x", "z"],
  "t": ["r", "y", "g", "f"],
  "u": ["y", "i", "j", "h"],
  "v": ["c", "f", "g", "b"],
  "w": ["q", "e", "s", "a"],
  "x": ["z", "s", "d", "c"],
  "y": ["t", "u", "h", "g"],
  "z": ["a", "s", "x"]
}
